skelebot/__init__.py
skelebot/common.py
skelebot/skelebot.py
skelebot/components/__init__.py
skelebot/components/bump.py
skelebot/components/componentFactory.py
skelebot/components/dexec.py
skelebot/components/environments.py
skelebot/components/jupyter.py
skelebot/components/kerberos.py
skelebot/components/package.py
skelebot/components/plugin.py
skelebot/components/prime.py
skelebot/components/registry.py
skelebot/components/repository/__init__.py
skelebot/components/repository/artifactRepo.py
skelebot/components/repository/artifactoryRepo.py
skelebot/components/repository/repository.py
skelebot/components/repository/s3Repo.py
skelebot/objects/__init__.py
skelebot/objects/arg.py
skelebot/objects/component.py
skelebot/objects/config.py
skelebot/objects/job.py
skelebot/objects/param.py
skelebot/objects/semver.py
skelebot/objects/skeleYaml.py
skelebot/systems/__init__.py
skelebot/systems/execution/__init__.py
skelebot/systems/execution/commandBuilder.py
skelebot/systems/execution/docker.py
skelebot/systems/execution/dockerCommand.py
skelebot/systems/execution/executor.py
skelebot/systems/generators/__init__.py
skelebot/systems/generators/dockerfile.py
skelebot/systems/generators/dockerignore.py
skelebot/systems/generators/readme.py
skelebot/systems/generators/yaml.py
skelebot/systems/parsing/__init__.py
skelebot/systems/parsing/skeleParser.py
skelebot/systems/scaffolding/__init__.py
skelebot/systems/scaffolding/prompt.py
skelebot/systems/scaffolding/scaffolder.py
skelebot/systems/scaffolding/templates/python/template.yaml
skelebot/systems/scaffolding/templates/python_dash/template.yaml
skelebot/systems/scaffolding/templates/python_dash/files/app_py
skelebot/systems/scaffolding/templates/python_dash/files/config_py
skelebot/systems/scaffolding/templates/python_dash/files/server_py
skelebot/systems/scaffolding/templates/python_dash/files/style_css
skelebot-2.3.0.dist-info/METADATA
skelebot-2.3.0.dist-info/WHEEL
skelebot-2.3.0.dist-info/entry_points.txt
skelebot-2.3.0.dist-info/licenses/LICENSE
skelebot-2.3.0.dist-info/RECORD
