Metadata-Version: 2.4
Name: skelebot
Version: 2.3.0
Summary: ML Build Tool
Project-URL: Homepage, https://github.com/carsdotcom/skelebot
Project-URL: Documentation, https://carsdotcom.github.io/skelebot/
Project-URL: Issues, https://github.com/carsdotcom/skelebot/issues
Project-URL: Changelog, https://github.com/carsdotcom/skelebot/blob/master/CHANGELOG.md
Author-email: Sean Shookman <sshookman@cars.com>, Joao Moreira <jmoreira@cars.com>
License: MIT License
License-File: LICENSE
Requires-Python: >=3.9
Requires-Dist: boto3>=1.10
Requires-Dist: colorama>=0.4.1
Requires-Dist: dohq-artifactory>=0.1.17
Requires-Dist: pyyaml>=5.1.2
Requires-Dist: schema>=0.7.0
Requires-Dist: tomli>=1.1.0; python_version < '3.11'
Provides-Extra: dev
Requires-Dist: coverage~=7.5; extra == 'dev'
Requires-Dist: pytest~=8.2; extra == 'dev'
